xprocess/__init__.py
xprocess/pytest_xprocess.py
xprocess/xprocess.py
pytest_xprocess-1.0.2.dist-info/LICENSE
pytest_xprocess-1.0.2.dist-info/METADATA
pytest_xprocess-1.0.2.dist-info/WHEEL
pytest_xprocess-1.0.2.dist-info/entry_points.txt
pytest_xprocess-1.0.2.dist-info/top_level.txt
pytest_xprocess-1.0.2.dist-info/RECORD
